packageTest/__init__.py
packageTest/packageTest.py
acng-1.0.0.3.dist-info/LICENSE
acng-1.0.0.3.dist-info/METADATA
acng-1.0.0.3.dist-info/WHEEL
acng-1.0.0.3.dist-info/top_level.txt
acng-1.0.0.3.dist-info/RECORD
