Metadata-Version: 2.1
Name: acng
Version: 1.0.0.3
Summary: Make Clone name
Home-page: https://novelier-webbelier.github.io
Author: Novelier Webbelier
Author-email: Novelier.Webbelier@gmail.com
License: MIT
Platform: UNKNOWN
Requires-Python: >=3
